abi_ds_utils/__init__.py
abi_ds_utils/airflow.py
abi_ds_utils/aws.py
abi_ds_utils/spark.py
abi_ds_utils-1.2.3.dist-info/WHEEL
abi_ds_utils-1.2.3.dist-info/METADATA
abi_ds_utils-1.2.3.dist-info/RECORD
