Metadata-Version: 2.1
Name: abi-ds-utils
Version: 1.2.3
Summary: Utility modules for working with spark, containers, aws and more.
License: Private
Author: Martin Matousek
Requires-Python: >=3.8,<4.0
Classifier: License :: Other/Proprietary License
Classifier: Programming Language :: Python :: 3
Classifier: Programming Language :: Python :: 3.10
Classifier: Programming Language :: Python :: 3.8
Classifier: Programming Language :: Python :: 3.9
Requires-Dist: boto3 (>=1.21.14,<2.0.0)
Requires-Dist: pyarrow (>=7.0.0)
Requires-Dist: pyspark (==3.3.2)
